PC_Adder.v
// Copyright 2023 MERL-DSU

//    Licensed under the Apache License, Version 2.0 (the "License");
//    you may not use this file except in compliance with the License.
//    You may obtain a copy of the License at

//        http://www.apache.org/licenses/LICENSE-2.0

//    Unless required by applicable law or agreed to in writing, software
//    distributed under the License is distributed on an "AS IS" BASIS,
//    WITHOUT WARRANTIES OR CONDITIONS OF ANY KIND, either express or implied.
//    See the License for the specific language governing permissions and
//    limitations under the License.

module PC_Adder(a,b,c);

    input [31:0]a,b;
    output [31:0]c;

    assign c = a + b;
    
endmodule

Instruction_Memory.v
module Instruction_Memory(rst,A,RD);

  input rst;
  input [31:0]A;
  output [31:0]RD;

  reg [31:0] mem [1023:0];
  
  assign RD = (rst == 1'b0) ? {32{1'b0}} : mem[A[31:2]];

//  initial begin
//    $readmemh("memfile.hex",mem);             //Commented cuz vivado doesnt support hex file
//  end

/////////////////////////////////////////////////////////////////////////////////////////////
//under opcode 0110011:           this opcode --> ALUOP = 10
//    1. func3 = 000 and ({op[5],funct7[5]} != 2'b11)  --> Addition
//    2. func3 = 000 and ({op[5],funct7[5]} == 2'b11)  --> Subtraction
//    3. func3 = 001 --> Normal 2d convolution
//    4. func3 = 010 --> Pruned winograd convolution
//    5. func3 = 011 --> Non pre processed winograd convolution
//    6. funct3 = 3'b110  --> OR logic
//    7. funct3 = 3'b111  --> AND logic
/////////////////////////////////////////////////////////////////////////////////////////////

  initial begin
               
        mem[0] = 32'h001020ab;          //Start of Input Matrix data //New matrix --> Calculation in sanjana book
        mem[1] = 32'h003010ab;
        mem[2] = 32'h003010ab;
        mem[3] = 32'h002010ab;
        mem[4] = 32'h004020ab;
        mem[5] = 32'h001030ab;
        mem[6] = 32'h003020ab;
        mem[7] = 32'h004010ab;
        mem[8] = 32'h001000ab;          //Start of Kernel data
        mem[9] = 32'h0FF000ab;
        mem[10] = 32'h001000ab;
        mem[11] = 32'h0FF000ab;
        mem[12] = 32'h001000ab;
        mem[13] = 32'h0FF000ab;         //Loading data ends here
        //mem[14] = 32'h00119133;       //Temporarily used linear_conv's opcode for wino , should be updated
        mem[14] = 32'h00003033;         //uncomment for normal winograd convolution as output
        //mem[14] = 32'h00001033;       //uncomment for normal convolution as output
        //mem[14] = 32'h00002033;       //uncomment for pruned winograd convolution as output
        
  end

endmodule

PC.v
// Copyright 2023 MERL-DSU

//    Licensed under the Apache License, Version 2.0 (the "License");
//    you may not use this file except in compliance with the License.
//    You may obtain a copy of the License at

//        http://www.apache.org/licenses/LICENSE-2.0

//    Unless required by applicable law or agreed to in writing, software
//    distributed under the License is distributed on an "AS IS" BASIS,
//    WITHOUT WARRANTIES OR CONDITIONS OF ANY KIND, either express or implied.
//    See the License for the specific language governing permissions and
//    limitations under the License.



module PC_Module(clk,rst,PC,PC_Next);
    input clk,rst;
    input [31:0]PC_Next;
    output [31:0]PC;
    reg [31:0]PC;

    always @(posedge clk)
    begin
        if(rst == 1'b0)
            PC <= {32{1'b0}};
        else
            PC <= PC_Next;
    end
endmodule

Fetch_Cycle.v
// Copyright 2023 MERL-DSU

//    Licensed under the Apache License, Version 2.0 (the "License");
//    you may not use this file except in compliance with the License.
//    You may obtain a copy of the License at

//        http://www.apache.org/licenses/LICENSE-2.0

//    Unless required by applicable law or agreed to in writing, software
//    distributed under the License is distributed on an "AS IS" BASIS,
//    WITHOUT WARRANTIES OR CONDITIONS OF ANY KIND, either express or implied.
//    See the License for the specific language governing permissions and
//    limitations under the License.
//`include "Mux.v"
//`include "PC.v"
//`include "Instruction_Memory.v"
//`include "PC_Adder.v"

module fetch_cycle(clk, rst, PCSrcE, PCTargetE, InstrD, PCD, PCPlus4D);

    // Declare input & outputs
    input clk, rst;
    input PCSrcE;
    input [31:0] PCTargetE;
    output [31:0] InstrD;
    output [31:0] PCD, PCPlus4D;

    // Declaring interim wires
    wire [31:0] PC_F, PCF, PCPlus4F;
    wire [31:0] InstrF;

    // Declaration of Register
    reg [31:0] InstrF_reg;
    reg [31:0] PCF_reg, PCPlus4F_reg;


    // Initiation of Modules
    // Declare PC Mux
    Mux PC_MUX (.a(PCPlus4F),
                .b(PCTargetE),
                .s(PCSrcE),
                .c(PC_F)
                );

    // Declare PC Counter
    PC_Module Program_Counter (
                .clk(clk),
                .rst(rst),
                .PC(PCF),
                .PC_Next(PC_F)
                );

    // Declare Instruction Memory
    Instruction_Memory IMEM (
                .rst(rst),
                .A(PCF),
                .RD(InstrF)
                );

    // Declare PC adder
    PC_Adder PC_adder (
                .a(PCF),
                .b(32'h00000004),
                .c(PCPlus4F)
                );

    // Fetch Cycle Register Logic
    always @(posedge clk or negedge rst) begin
        if(rst == 1'b0) begin
            InstrF_reg <= 32'h00000000;
            PCF_reg <= 32'h00000000;
            PCPlus4F_reg <= 32'h00000000;
        end
        else begin
            InstrF_reg <= InstrF;
            PCF_reg <= PCF;
            PCPlus4F_reg <= PCPlus4F;
        end
    end


    // Assigning Registers Value to the Output port
    assign  InstrD = (rst == 1'b0) ? 32'h00000000 : InstrF_reg;
    assign  PCD = (rst == 1'b0) ? 32'h00000000 : PCF_reg;
    assign  PCPlus4D = (rst == 1'b0) ? 32'h00000000 : PCPlus4F_reg;


endmodule

Fetch_cycle_tb.v
module tb();

// Declare I/O

reg clk =1, rst, PCSrcE;

reg [31:0] PCTargetE;

wire [31:0] InstrD, PCD, PCPlus4D;

// Declare the design under test

fetch_cycle dut (

.clk(clk),

.rst(rst),

.PCSrcE (PCSrcE),

.PCTargetE (PCTargetE),

.InstrD(InstrD),

.PCD (PCD),

.PCPlus4D (PCPlus4D)

);

always begin
 clk = ~clk; #50;

end

// Provide the Stimulus

initial begin

rst <= 1'b0;

#200;

rst <=1'b1;

PCSrcE <= 1'b0;
PCTargetE <= 32'h00000000;

#500;

$finish;
end
initial begin
$dumpfile("dump.vcd");
$dumpvars(0);

end
endmodule

Mux.v
// Copyright 2023 MERL-DSU

//    Licensed under the Apache License, Version 2.0 (the "License");
//    you may not use this file except in compliance with the License.
//    You may obtain a copy of the License at

//        http://www.apache.org/licenses/LICENSE-2.0

//    Unless required by applicable law or agreed to in writing, software
//    distributed under the License is distributed on an "AS IS" BASIS,
//    WITHOUT WARRANTIES OR CONDITIONS OF ANY KIND, either express or implied.
//    See the License for the specific language governing permissions and
//    limitations under the License.

module Mux (a,b,s,c);

    input [31:0]a,b;
    input s;
    output [31:0]c;

    assign c = (~s) ? a : b ;
endmodule

module Mux_3_by_1 (a,b,c,s,d);
    input [31:0] a,b,c;
    input [1:0] s;
    output [31:0] d;

    assign d = (s == 2'b00) ? a : (s == 2'b01) ? b : (s == 2'b10) ? c : 32'h00000000;
endmodule

dump.vcd
$date
	Thu Dec 21 13:59:16 2023
$end
$version
	Icarus Verilog
$end
$timescale
	1s
$end
$scope module Mux_3_by_1 $end
$var wire 32 ! a [31:0] $end
$var wire 32 " b [31:0] $end
$var wire 32 # c [31:0] $end
$var wire 2 $ s [1:0] $end
$var wire 32 % d [31:0] $end
$upscope $end
$scope module tb $end
$var wire 32 & PCPlus4D [31:0] $end
$var wire 32 ' PCD [31:0] $end
$var wire 32 ( InstrD [31:0] $end
$var reg 1 ) PCSrcE $end
$var reg 32 * PCTargetE [31:0] $end
$var reg 1 + clk $end
$var reg 1 , rst $end
$scope module dut $end
$var wire 1 ) PCSrcE $end
$var wire 32 - PCTargetE [31:0] $end
$var wire 1 + clk $end
$var wire 1 , rst $end
$var wire 32 . PC_F [31:0] $end
$var wire 32 / PCPlus4F [31:0] $end
$var wire 32 0 PCPlus4D [31:0] $end
$var wire 32 1 PCF [31:0] $end
$var wire 32 2 PCD [31:0] $end
$var wire 32 3 InstrF [31:0] $end
$var wire 32 4 InstrD [31:0] $end
$var reg 32 5 InstrF_reg [31:0] $end
$var reg 32 6 PCF_reg [31:0] $end
$var reg 32 7 PCPlus4F_reg [31:0] $end
$scope module IMEM $end
$var wire 1 , rst $end
$var wire 32 8 RD [31:0] $end
$var wire 32 9 A [31:0] $end
$upscope $end
$scope module PC_MUX $end
$var wire 32 : b [31:0] $end
$var wire 1 ) s $end
$var wire 32 ; c [31:0] $end
$var wire 32 < a [31:0] $end
$upscope $end
$scope module PC_adder $end
$var wire 32 = b [31:0] $end
$var wire 32 > c [31:0] $end
$var wire 32 ? a [31:0] $end
$upscope $end
$scope module Program_Counter $end
$var wire 32 @ PC_Next [31:0] $end
$var wire 1 + clk $end
$var wire 1 , rst $end
$var reg 32 A PC [31:0] $end
$upscope $end
$upscope $end
$upscope $end
$enddefinitions $end
#0
$dumpvars
bx A
bx @
bx ?
bx >
b100 =
bx <
bx ;
bx :
bx 9
b0 8
b0 7
b0 6
b0 5
b0 4
b0 3
b0 2
bx 1
b0 0
bx /
bx .
bx -
0,
0+
bx *
x)
b0 (
b0 '
b0 &
bx %
bz $
bz #
bz "
bz !
$end
#50
b100 /
b100 <
b100 >
b0 1
b0 9
b0 ?
b0 A
1+
#100
0+
#150
1+
#200
b10100000000001010010011 3
b10100000000001010010011 8
b100 .
b100 ;
b100 @
b0 *
b0 -
b0 :
0)
1,
0+
#250
b1100000000001100010011 3
b1100000000001100010011 8
b1000 .
b1000 ;
b1000 @
b100 &
b100 0
b10100000000001010010011 (
b10100000000001010010011 4
b1000 /
b1000 <
b1000 >
b100 1
b100 9
b100 ?
b100 A
b100 7
b10100000000001010010011 5
1+
#300
0+
#350
b11000101000001110110011 3
b11000101000001110110011 8
b1100 .
b1100 ;
b1100 @
b1000 &
b1000 0
b100 '
b100 2
b1100000000001100010011 (
b1100000000001100010011 4
b1100 /
b1100 <
b1100 >
b1000 1
b1000 9
b1000 ?
b1000 A
b1000 7
b100 6
b1100000000001100010011 5
1+
#400
0+
#450
b10010000000011 3
b10010000000011 8
b10000 .
b10000 ;
b10000 @
b1100 &
b1100 0
b1000 '
b1000 2
b11000101000001110110011 (
b11000101000001110110011 4
b10000 /
b10000 <
b10000 >
b1100 1
b1100 9
b1100 ?
b1100 A
b1100 7
b1000 6
b11000101000001110110011 5
1+
#500
0+
#550
b100000000010010010011 3
b100000000010010010011 8
b10100 .
b10100 ;
b10100 @
b10000 &
b10000 0
b1100 '
b1100 2
b10010000000011 (
b10010000000011 4
b10100 /
b10100 <
b10100 >
b10000 1
b10000 9
b10000 ?
b10000 A
b10000 7
b1100 6
b10010000000011 5
1+
#600
0+
#650
b100101000000010100110011 3
b100101000000010100110011 8
b11000 .
b11000 ;
b11000 @
b10100 &
b10100 0
b10000 '
b10000 2
b100000000010010010011 (
b100000000010010010011 4
b11000 /
b11000 <
b11000 >
b10100 1
b10100 9
b10100 ?
b10100 A
b10100 7
b10000 6
b100000000010010010011 5
1+
